flask_tui_editor/__init__.py
flask_tui_editor/ext.py
flask_tui_editor/fields.py
flask_tui_editor/widgets.py
flask_tui_editor/static/css/toastui-editor-dark.min.css
flask_tui_editor/static/css/toastui-editor.min.css
flask_tui_editor/static/js/toastui-editor-all.min.js
flask_tui_editor/static/js/toastui-editor-init.js
flask_tui_editor/static/js/i18n/ar.js
flask_tui_editor/static/js/i18n/cs-cz.js
flask_tui_editor/static/js/i18n/de-de.js
flask_tui_editor/static/js/i18n/es-es.js
flask_tui_editor/static/js/i18n/fi-fi.js
flask_tui_editor/static/js/i18n/fr-fr.js
flask_tui_editor/static/js/i18n/gl-es.js
flask_tui_editor/static/js/i18n/hr-hr.js
flask_tui_editor/static/js/i18n/it-it.js
flask_tui_editor/static/js/i18n/ja-jp.js
flask_tui_editor/static/js/i18n/ko-kr.js
flask_tui_editor/static/js/i18n/nb-no.js
flask_tui_editor/static/js/i18n/nl-nl.js
flask_tui_editor/static/js/i18n/pl-pl.js
flask_tui_editor/static/js/i18n/pt-br.js
flask_tui_editor/static/js/i18n/ru-ru.js
flask_tui_editor/static/js/i18n/sv-se.js
flask_tui_editor/static/js/i18n/tr-tr.js
flask_tui_editor/static/js/i18n/uk-ua.js
flask_tui_editor/static/js/i18n/zh-cn.js
flask_tui_editor/static/js/i18n/zh-tw.js
flask_tui_editor/static/js/plugins/toastui-editor-plugin-chart.min.js
flask_tui_editor/static/js/plugins/toastui-editor-plugin-code-syntax-highlight.min.js
flask_tui_editor/static/js/plugins/toastui-editor-plugin-color-syntax.min.js
flask_tui_editor/static/js/plugins/toastui-editor-plugin-table-merged-cell.min.js
flask_tui_editor/static/js/plugins/toastui-editor-plugin-uml.min.js
Flask_TUI_Editor-1.0.0.dist-info/LICENSE
Flask_TUI_Editor-1.0.0.dist-info/METADATA
Flask_TUI_Editor-1.0.0.dist-info/WHEEL
Flask_TUI_Editor-1.0.0.dist-info/top_level.txt
Flask_TUI_Editor-1.0.0.dist-info/RECORD
